{
    "manifestVersion": 1,
    "id": "website-transform",
    "name": "Website Transform",
    "version": "3.0.1",
    "public": true,
    "publisher": "luuksommers",
    "targets": [
        { "id": "Microsoft.VisualStudio.Services" }
    ],
    "description": "Task to apply XDT transform on XML files. This is a fork from the original from https://github.com/qetza/vsts-xdttransform-task with wildcard support",
    "categories": [
        "Build and release"
    ],
    "tags": [
        "release",
        "build",
        "xdt",
        "transform",
        "configuration"
    ],
    "links": {
        "support": { "uri": "https://github.com/luuksommers/vsts-website-transform/issues" }
    },
    "icons": {
        "default": "images/extension-icon.png"
    },
    "branding": {
        "color": "#1C3272",
        "theme": "dark"
    },
    "screenshots": [
        { "path": "images/screenshot-01.png" }
    ],
    "repository": {
        "type": "git",
        "uri": "https://github.com/luuksommers/vsts-website-transform"
    },
    "content": {
        "details": { "path": "README.md" },
        "license": { "path": "LICENSE.txt" }
    },
    "files": [
        { "path": "task" },
        {
            "path": "images",
            "addressable": true
        }
    ],
    "contributions": [
        {
            "id": "website-transform-task",
            "type": "ms.vss-distributed-task.task",
            "targets": [
                "ms.vss-distributed-task.tasks"
            ],
            "properties": { "name": "task" }
        }
    ]
}